dashcutter.py
dashcutter-0.1.4.dist-info/entry_points.txt
dashcutter-0.1.4.dist-info/METADATA
dashcutter-0.1.4.dist-info/WHEEL
dashcutter-0.1.4.dist-info/RECORD
