Metadata-Version: 2.3
Name: dashcutter
Version: 0.1.4
Summary: This package is for creating different dash ui's
Author: Millicent Malinga
Author-email: millicent.malinga@ansys.com
Requires-Python: >=3.10
Classifier: Programming Language :: Python :: 3
Classifier: Programming Language :: Python :: 3.10
Classifier: Programming Language :: Python :: 3.11
Classifier: Programming Language :: Python :: 3.12
Classifier: Programming Language :: Python :: 3.13
Requires-Dist: click (>=8.2.1,<9.0.0)
Requires-Dist: cookiecutter (>=2.6.0,<3.0.0)
